setup.py
src/jldcmds/__init__.py
src/jldcmds/do_checks.py
src/jldcmds/do_checks2.py
src/jldcmds/script_jwrite.py
src/jldcmds/script_wscan.py
src/jldcmds/script_wsniff.py
src/jldcmds.egg-info/PKG-INFO
src/jldcmds.egg-info/SOURCES.txt
src/jldcmds.egg-info/dependency_links.txt
src/jldcmds.egg-info/not-zip-safe
src/jldcmds.egg-info/requires.txt
src/jldcmds.egg-info/top_level.txt
src/jldcmds/common/__init__.py
src/jldcmds/common/do_setup.py
src/jldcmds/common/tools_misc.py
src/jldcmds/common/tools_os.py
src/jldcmds/common/tools_sys.py
src/jldcmds/lib/__init__.py
src/jldcmds/lib/utilities.py
src/jldcmds/network/__init__.py
src/jldcmds/network/constants.py
src/jldcmds/network/scapy_ex.py
src/jldcmds/network/wlan.py
src/scripts/jldcmd-jwrite
src/scripts/jldcmd-wscan
src/scripts/jldcmd-wsniff