Metadata-Version: 1.0
Name: jldcmds
Version: 0.4
Summary: Collection of command line tools
Home-page: https://github.com/jldupont/jldcmds
Author: Jean-Lou Dupont
Author-email: jl@jldupont.com
License: UNKNOWN
Platform: UNKNOWN
